extended_pathlib.py
extended_pathlib-0.5.0.dist-info/LICENSE
extended_pathlib-0.5.0.dist-info/METADATA
extended_pathlib-0.5.0.dist-info/WHEEL
extended_pathlib-0.5.0.dist-info/top_level.txt
extended_pathlib-0.5.0.dist-info/RECORD
