Metadata-Version: 2.1
Name: extended-pathlib
Version: 0.5.0
Summary: shell library
Home-page: http://nurdletech.com/linux-utilities/extended_pathlib
Author: Ken Kundert
Author-email: extended_pathlib@nurdletech.com
License: GPLv3+
Download-URL: https://github.com/kenkundert/extended_pathlib/tarball/master
Keywords: extended,pathlib
Platform: UNKNOWN
Classifier: Development Status :: 4 - Beta
Classifier: Intended Audience :: Developers
Classifier: License :: OSI Approved :: GNU General Public License v3 or later (GPLv3+)
Classifier: Natural Language :: English
Classifier: Operating System :: POSIX :: Linux
Classifier: Programming Language :: Python :: 3.6
Classifier: Programming Language :: Python :: 3.7
Classifier: Programming Language :: Python :: 3.8
Classifier: Programming Language :: Python :: 3.9
Classifier: Topic :: Utilities
Requires-Dist: six
